__init__.py
download_ipindia_data.py
insert_into_db.py
magpie.py
hash_files/__init__.py
hash_files/industry.py
hash_files/ipc.py
hash_files/sector.py
hash_files/sub_sector.py
tools/ipindia_sequence_generator.py
incubig_magpie-1.0.0.dist-info/METADATA
incubig_magpie-1.0.0.dist-info/WHEEL
incubig_magpie-1.0.0.dist-info/top_level.txt
incubig_magpie-1.0.0.dist-info/RECORD
